<?xml version="1.0" encoding="UTF-8"?>
<svg version="1.1" viewBox="0 0 160 200" xmlns="http://www.w3.org/2000/svg" >
  <path id="firstFillColor" d="m 50.144088,166.1523 -7.608075,9.5214 -1.32565,0.8893 -1.037464,0.3662 -1.671471,0.5754 -1.786744,0.2616 -2.593662,-0.1046 -2.63111,-0.2871 -3.074946,-1.073 -2.305478,-1.151 -2.708935,-1.831 -1.844382,-1.5694 -1.729108,-1.6741 -0.979827,-1.3079 -0.979828,-1.7787 -0.57637,-2.3542 -0.115272,-2.4064 z" style="stroke-width:1.17292368" />
  <path id="secondFillColor" d="m 50.144088,166.1523 7.262253,-10.0444 -9.711219,-0.9307 -7.57986,3.5987 h -0.806916 l -0.634007,-0.4708 -0.806918,-1.7787 -0.521784,-2.3553 -16.020013,-1.516 -0.979828,1.6217 -0.979828,1.3079 -0.864553,1.3079 -0.806917,1.3079 -0.345822,1.2555 -0.230548,0.994 0.05764,1.7788 z" style="stroke-width:1.17292368" />
  <path id="firstFillColor1" d="m 57.406341,156.1079 5.129685,-6.5394 -1.095101,-1.1509 -0.576369,0.1569 -20.403473,10.7246 h -1.440922 l -1.037465,-0.6278 -0.74928,-1.831 -0.518732,-2.1449 0.568112,-1.4813 0.181167,-4.0641 -0.17291,-1.2033 -0.345821,-0.3662 -1.383287,-2.0403 -1.959655,-2.1972 -1.498561,-1.7264 -1.530325,-2.0524 -9.24778,13.0909 15.446697,1.7787 0.345821,2.0403 0.749279,1.5694 0.518733,0.7847 0.806917,0.4709 h 1.152738 l 8.242082,-3.9236 z" style="stroke-width:1.17292368" />
  <path id="firstFillColor3" d="m 68.126805,139.681 c 0.23055,-0.3662 2.0173,-3.1389 2.0173,-3.1389 l -20.922209,-3.8713 3.804038,7.5856 0.749279,0.7848 2.017293,0.994 1.383286,0.1569 2.523235,-0.8402 3.009911,-1.1478 2.939486,-0.7324 z" style="stroke-width:1.17292368" />
  <path id="secondFillColor1" d="m 70.144105,136.5421 11.239195,-12.6601 0.4611,-0.5755 -36.023083,-4.0806 -2.593662,2.825 5.994241,10.6199 z" style="stroke-width:1.17292368" />
  <path id="firstFillColor4" d="m 81.8444,123.3065 14.409225,-16.8977 -34.582153,-6.5394 -15.850155,19.3565 z" style="stroke-width:1.17292368" />
  <path id="secondFillColor2" d="m 96.253625,106.4088 12.161395,-12.2417 -37.521634,-5.2838 -9.221914,10.9861 z" style="stroke-width:1.17292368" />
  <path id="firstFillColor5" d="m 108.41502,94.1671 2.88185,-2.5635 -0.28819,-36.2018 -2.13257,0.9417 -3.05475,1.8833 -5.41787,3.3482 -4.092215,3.0866 -11.008654,9.312 -7.031713,7.3763 -7.377522,7.5334 z" style="stroke-width:1.17292368" />
  <path id="secondFillColor3" d="m 111.29687,91.6036 2.47838,-1.4125 1.67147,-0.7847 1.15274,-0.5231 1.32565,-0.1047 15.15852,-32.3305 -5.93661,-1.7787 -4.95677,-0.9417 -1.84438,-0.052 -2.88185,0.052 -2.1902,0.3139 -2.24784,0.5755 -2.0173,0.7847 z" style="stroke-width:1.17292368" />
  <path id="firstFillColor6" d="m 117.92511,88.7786 2.6513,0.9417 1.21039,0.8894 1.90201,1.5694 1.21037,1.2033 34.29397,-12.0848 -1.03745,-2.9296 -0.97983,-2.6158 -2.13257,-3.5573 -1.78674,-2.0926 -3.68877,-3.9759 -2.59366,-2.2496 -3.80405,-2.6157 -4.95677,-2.6681 -2.65129,-1.2555 -2.47839,-0.8894 z" style="stroke-width:1.17292368" />
  <path id="secondFillColor4" d="m 124.89918,93.3824 0.74929,1.0463 0.23054,1.0986 0.28818,1.0463 -0.23054,1.8833 -0.34583,1.7264 -0.46108,1.1509 34.17868,-6.4347 0.51875,-3.5051 0.11523,-3.1912 0.0576,-2.5635 -0.28818,-1.9879 -0.51874,-2.3542 z" style="stroke-width:1.17292368" />
  <path id="firstFillColor7" d="m 125.12974,101.3342 -1.38329,3.3482 -3.86169,8.0565 25.12971,11.1431 2.70895,-3.3482 2.70892,-3.9236 2.30549,-3.5574 2.24783,-4.3422 1.84438,-4.3421 1.44093,-4.5514 0.86455,-3.4005 0.1729,-1.5171 z" style="stroke-width:1.17292368" />
  <path id="secondFillColor5" d="m 119.88476,112.7389 -1.0951,2.3542 -0.634,2.2495 -0.40346,2.2495 -0.0576,1.9357 0.34582,1.8309 0.69165,1.5696 1.21037,1.831 1.38329,1.3078 1.95966,1.5171 2.47838,1.5171 2.13257,0.8894 1.90202,0.2616 1.95965,-0.157 2.70894,-0.5231 2.59366,-1.0986 2.24784,-1.3602 2.47838,-1.9357 1.72911,-1.7786 1.49856,-1.5171 z" style="stroke-width:1.17292368" />
  <path id="firstFillColor8" d="m 49.615964,41.1024 -3.506461,-4.2201 -2.478388,-3.0866 1.268012,-1.7787 3.285305,-3.4004 2.708935,-3.2436 1.32565,-2.4063 v -1.6218 l -0.806917,-1.1509 -0.922191,-0.7848 -1.440923,-0.1569 -2.017293,0.2616 -2.997119,1.4648 -6.801158,4.1852 -1.268013,0.7846 -3.582066,-4.525 4.850079,-8.9721 1.671471,-3.819 0.634006,-2.6158 v -1.5694 l -0.691643,-1.2556 -0.979829,-0.7324 -1.037463,-0.4185 -1.268013,-0.157 -1.729108,0.157 -1.037466,0.4708 -0.979826,0.6278 -1.210376,1.4125 -1.095102,1.6218 -1.152738,1.8833 -1.613834,3.1912 -0.403458,0.4708 -0.288184,0.052 -3.919313,-7.8473 -1.325649,-2.0403 -1.095101,-0.7847 -1.383286,-0.6801 -1.268013,-0.3139 -0.922191,-0.1046 -0.806917,0.1046 -0.864554,0.3662 -0.806917,0.6801 -1.152738,0.9417 -0.523297,0.7246 0.0046,1.0541 0.288185,1.6741 0.05764,1.6741 0.288186,1.5694 0.345821,1.4648 0.634005,1.5695 0.288186,0.837 v 0.4709 l -0.172912,0.3662 -0.345821,0.052 -0.576369,-0.1047 -1.037465,-0.2092 -5.5331447,-1.2033 c 0,0 -1.7867456,-0.1569 -2.2478408,-0.2092 -0.4610952,-0.052 -2.0172928,0.1569 -2.0172928,0.1569 l -0.9221903,0.8894 -0.63400625,0.6801 -0.23054809,0.5231 -0.17291006,0.8894 v 0.6278 l 0.05764002,1.3078 0.74928028,1.3602 0.7492793,1.0986 1.6138336,1.2556 1.0374654,0.3662 c 0,0 0.9798273,0.1569 1.3832855,0.3662 0.4034581,0.2093 1.6714706,0.1046 2.1325668,0.3139 0.4610952,0.2093 10.6628321,-0.157 10.6628321,-0.157 l 0.576368,0.2093 2.132567,2.4588 2.305478,3.7666 1.440922,2.4065 0.806918,2.5111 -0.230548,1.0463 -0.403459,0.3662 h -0.922191 l -9.913551,-0.2616 -3.631126,0.052 -2.1325668,0.5232 -1.3256495,0.6278 -0.9221904,0.6277 -1.3256495,0.994 -0.8645543,1.3079 -0.4610962,1.5171 v 1.151 l 0.4610962,0.7324 0.8645543,0.7847 0.9798274,0.7847 1.7291086,0.994 1.7291077,0.5232 2.3054765,0.5754 1.959655,0.2093 2.593662,0.2092 4.610955,0.2616 1.652805,0.042 1.517226,-2.1344 1.331886,-0.9435 1.953419,-1.3583 2.247839,-1.0463 1.959657,-0.5232 2.305476,-0.4708 2.190203,0.1046 2.017293,0.5231 2.363115,1.0987 1.556197,1.0986 1.273796,1.0856 z" style="stroke-width:1.17292368" />
  <path id="firstFillColor9" d="m 69.826725,42.72 7.349083,-6.1516 -5.360232,-8.4227 -0.97983,-2.3018 -0.0576,-2.0402 0.80691,-1.2556 0.74928,-0.6801 1.325651,-0.4185 1.44092,0.157 1.152741,0.4185 1.5562,1.2032 8.331623,7.5111 4.618772,-4.1104 -2.806291,-8.9461 -0.86455,-5.5453 0.23054,-2.4065 0.63401,-1.5172 0.80692,-0.7847 1.325641,-0.4708 1.959661,0.052 1.72911,0.5232 1.440931,1.4125 1.0951,2.2495 1.095101,2.7204 0.57637,2.9296 0.64873,2.1804 7.189884,-8.8244 1.95965,-1.0986 1.72911,-0.4185 1.5562,-0.052 1.26802,0.5231 1.21037,0.9417 0.74928,1.7264 0.23054,1.4125 -0.28818,1.6217 -0.634,1.2556 -3.33818,6.3632 9.50532,-0.2947 1.61385,0.3139 1.38328,0.7847 0.80692,1.3602 0.23054,1.7263 -0.34581,1.3602 -0.9222,1.2556 -1.44092,1.4648 -1.21039,0.6801 -1.78674,0.2616 -1.84439,0.052 -1.84437,-0.2616 -2.53602,-0.2616 -7.79888,-1.72 -7.129085,6.7946 -1.7291,2.1449 -0.691661,1.3602 v 0.5754 l 0.518741,0.5232 0.97983,0.3662 2.420741,0.4185 6.397704,0.4185 2.42075,0.4709 2.24784,0.837 2.24785,1.3079 2.19019,1.9356 0.92219,2.0926 0.11523,1.5695 -0.63401,1.0986 -1.67147,1.3079 -1.7291,0.7324 -2.30548,0.5231 h -4.3804 l -3.63113,-0.3139 -3.515855,-0.6277 -1.72911,-0.3662 -1.210371,-1.6218 -1.32566,-1.9357 -1.383281,-1.3078 c 0,0 -1.78674,-0.994 -1.95966,-1.2556 -0.1729,-0.2616 -2.536011,-1.4125 -2.536011,-1.4125 l -2.305491,-0.6278 -2.074921,-0.3139 -1.902021,0.3662 -3.515861,0.9417 -1.10106,0.5822 -2.414791,-1.3669 -1.844381,-0.8371 z" style="stroke-width:1.17292368" />
  <path id="secondFillColor6" d="m 84.365481,59.48 6.989002,0.3686 2.074931,-0.5755 1.325661,-0.7847 0.86455,-1.5695 v -2.3018 l -0.23055,-1.6741 -0.46109,-1.8833 c 0,0 -2.074991,-2.2496 -2.074991,-2.2496 l -1.383281,-1.3078 -2.766521,-1.6741 -1.72915,-0.994 -4.380412,-0.9417 -2.478341,0.6801 -1.671471,0.6801 -2.36908,0.5299 2.31144,2.2951 1.844381,2.6681 1.671471,2.9819 1.0951,2.4065 0.57637,1.988 z" style="stroke-width:1.17292368" />
  <path id="secondFillColor7" d="m 32.852559,54.7504 -5.763243,-0.4472 -3.054757,-0.6801 -2.017293,-1.0986 -0.806916,-1.4125 v -1.988 l 0.634006,-2.1972 1.152739,-2.0926 2.254077,-1.9898 4.201259,-2.4046 4.265133,-0.994 2.190203,0.1046 2.017293,0.5231 2.766572,1.5172 1.15274,0.6801 1.273796,1.0856 -3.060543,2.838 -1.671471,1.7264 -1.613833,1.8833 -1.873795,1.6151 -1.2386,2.5178 z" style="stroke-width:1.17292368" />
  <path id="firstFillColor10" d="m 40.623132,108.5463 -5.542743,-5.8448 -3.260437,-6.6586 c 0,0 -1.956262,-5.5488 -2.037773,-5.9188 -0.08151,-0.3699 -1.304175,-7.6943 -1.304175,-7.6943 l -0.570576,-6.6587 0.407555,-5.4747 1.467196,-6.3627 1.630219,-5.1789 2.247528,-4.8178 3.112395,-4.1329 2.628147,-3.0348 3.7177,-3.4129 6.497796,-2.254 8.695039,-0.1778 6.68389,0.7398 3.831022,0.7398 1.80481,0.8718 3.900952,1.8657 3.854501,2.936 2.584871,4.0185 2.026081,4.038 0.98982,4.2483 0.652081,3.2553 0.24453,3.4773 -0.16301,3.2553 0.58207,3.6032 -14.409235,14.9097 -11.44123,13.7442 -3.178927,-1.0358 -2.771371,-0.6658 -3.58648,0.148 -1.548709,0.1479 -3.341946,1.0358 -1.63022,1.7017 -1.385684,1.7016 z" style="stroke-width:1.17292368" />
  <path id="path9162" d="m 54.153946,65.9313 -0.407555,0.5919 -0.07015,1.0341 v 0 l 0.966773,-0.2203 0.570576,-0.8138 -0.163021,-0.296 -0.489067,-0.2219 -0.163021,0.6659 z" style="stroke-width:1.17292368" />
  <path id="path9164" d="m 61.734461,66.7451 -0.861675,1.4003 v 1e-4 l 1.106208,0.1533 0.652087,-0.6658 0.163023,-0.8139 -0.489066,-0.2959 z" style="stroke-width:1.17292368" />
  <path id="secondFillColor8" d="m 50.086451,101.125 -1.719782,0.097 -3.341946,1.0358 -0.58669,1.1692 -2.128962,0.9931 -0.300252,1.2409 -1.243917,2.1408 0.560735,2.3215 1.729108,2.7204 1.729109,0.9417 1.498559,0.6277 2.651299,1.151 10.518444,-12.9364 -3.178927,-1.0358 -2.771371,-0.6659 -1.6863,0.1991 z" style="stroke-width:1.17292368" />
  <path id="secondFillColor9" d="m 32.879503,189.06 -0.6605,-4.9637 -1.711058,-7.091 3.613077,0.6563 2.593662,0.1046 4.495679,-1.2032 3.22767,-2.9296 18.097993,-24.0649 13.453951,9.2019 c 0,0 2.108021,-1.7732 2.108021,-2.2963 0,-0.5232 1.152741,-3.976 1.152741,-3.976 l 0.81094,-3.07 12.445555,-10.8457 2.420751,-2.9297 1.15273,-1.8833 1.498571,3.8713 1.03746,3.4528 0.11523,3.2435 0.34583,4.0806 -0.23056,3.662 -0.69164,3.3482 -1.498561,3.662 -1.7291,3.2436 -1.613841,1.1509 -1.03745,4.2898 -0.11524,7.2195 -1.152731,8.5795 -0.34583,4.4991 -0.23054,1.7787 -3.919312,-1.2556 -6.224782,0.3139 -5.878972,0.2093 -3.869752,0.3626 -2.12449,-17.5218 h -0.806921 l 0.26302,5.9654 -12.642096,0.4279 -0.07049,-6.3933 -0.922192,0.2092 -1.959654,17.1593 -4.265134,-0.7325 -10.951016,0.1046 z" style="stroke-width:1.17292368" />
  <path id="secondFillColor10" d="m 22.074903,150.6148 c -0.115271,-0.9417 0,-6.8009 0,-7.2195 0,-0.4185 1.152739,-5.9639 1.49856,-6.6963 0.345823,-0.7324 2.881848,-7.3241 2.881848,-7.3241 l 6.455335,-12.0323 5.827966,-10.0416 2.02629,0.5007 0.560735,2.3215 1.729108,2.7204 1.729109,0.9416 4.149858,1.7787 -5.706057,6.487 -5.129685,-5.4407 -0.806917,0.6278 6.555644,6.2844 4.04955,7.6312 2.536025,4.9176 2.593662,4.1852 -4.553317,1.5695 -4.149859,1.988 -3.284784,1.7128 -2.248361,1.9492 -8.216209,-7.9117 -2.504259,-5.167 -0.691645,-2.6158 -0.922189,0.9417 4.118093,6.8411 z" style="stroke-width:1.17292368" />
  <path id="secondFillColor11" d="m 87.319902,117.3426 -17.175797,19.1995 -2.0173,3.1389 3.400581,1.7264 3.573491,3.4528 2.651301,1.7787 2.309501,2.7892 7.142953,-6.7652 5.533142,-5.2315 3.342941,-3.662 -1.613831,-3.7667 -2.07493,-4.8129 -2.420751,-5.0222 z" style="stroke-width:1.17292368" />
  <path id="firstFillColor11" d="m 47.08933,143.0815 -6.051356,2.4452 -2.248361,1.9492 -1.281935,3.4255 -0.162041,3.2697 0.521784,2.3553 1.440925,2.2495 4.207495,-1.9879 6.915237,-4.1145 -3.226473,-4.7791 4.380405,4.6037 9.279546,-3.9236 -3.669973,-4.7645 -3.41937,-2.7688 -2.99712,0.5754 z" style="stroke-width:1.17292368" />
  <path id="firstFillColor12" d="m 75.989977,158.7704 1.416381,-3.1334 1.15273,-4.6037 v -2.825 l -4.610951,-3.9759 -4.495682,-2.9297 -3.804031,-1.831 -4.38041,1.5171 -4.073431,2.8212 7.185826,5.9678 1.562515,1.186 4.777552,-3.6972 -4.081892,4.1534 z" style="stroke-width:1.17292368" />
  <path id="firstFillColor13" d="m 27.343388,199.8712 0.725757,-4.3703 2.881846,-3.662 1.928512,-2.7789 13.057089,-0.046 6.340075,0.3139 1.498546,1.8834 4.14986,4.8129 1.152739,3.8713 -15.24082,-0.024 -1.358616,-6.2536 0.464855,6.2536 z" style="stroke-width:1.17292368" />
  <path id="firstFillColor14" d="m 64.380409,200 1.037465,-3.5574 2.53602,-4.1852 2.585601,-2.7763 13.322195,-0.258 2.651311,-0.6278 3.919312,1.2556 4.265122,4.6037 0.80691,2.9297 0.25232,2.4869 h -15.592876 l 0.81606,-5.8351 -1.71678,5.8351 z" style="stroke-width:1.17292368" />
</svg>

